hasql/__init__.py
hasql/aiopg.py
hasql/aiopg_sa.py
hasql/asyncpg.py
hasql/asyncpgsa.py
hasql/asyncsqlalchemy.py
hasql/base.py
hasql/psycopg3.py
hasql/py.typed
hasql/utils.py
hasql/balancer_policy/__init__.py
hasql/balancer_policy/base.py
hasql/balancer_policy/greedy.py
hasql/balancer_policy/random_weighted.py
hasql/balancer_policy/round_robin.py
tests/mocks/__init__.py
tests/mocks/pool_manager.py
hasql-0.5.11.dist-info/LICENSE
hasql-0.5.11.dist-info/METADATA
hasql-0.5.11.dist-info/WHEEL
hasql-0.5.11.dist-info/top_level.txt
hasql-0.5.11.dist-info/RECORD
