Metadata-Version: 2.1
Name: hasql
Version: 0.5.11
Summary: hasql is a module for acquiring actual connections with masters and replicas
Home-page: UNKNOWN
Author: Vladislav Bakaev <vlad@bakaev.tech>, Dmitry Orlov <me@mosquito.su>
Author-email: vlad@bakaev.tech, me@mosquito.su
License: Apache 2
Project-URL: Source, https://github.com/aiokitchen/hasql
Project-URL: Tracker, https://github.com/aiokitchen/hasql/issues
Project-URL: Documentation, https://github.com/aiokitchen/hasql/blob/master/README.rst
Platform: all
Classifier: Development Status :: 5 - Production/Stable
Classifier: Framework :: AsyncIO
Classifier: Intended Audience :: Developers
Classifier: License :: OSI Approved :: Apache Software License
Classifier: Natural Language :: Russian
Classifier: Operating System :: MacOS
Classifier: Operating System :: Microsoft
Classifier: Operating System :: POSIX
Classifier: Programming Language :: Python :: 3
Classifier: Programming Language :: Python :: 3.10
Classifier: Programming Language :: Python :: 3.7
Classifier: Programming Language :: Python :: 3.8
Classifier: Programming Language :: Python :: 3.9
Classifier: Programming Language :: Python :: Implementation :: CPython
Classifier: Programming Language :: Python :: Implementation :: PyPy
Classifier: Programming Language :: Python
License-File: LICENSE
Provides-Extra: aiopg
Requires-Dist: aiopg ; extra == 'aiopg'
Provides-Extra: aiopg_sa
Requires-Dist: aiopg[sa] ; extra == 'aiopg_sa'
Provides-Extra: asyncpg
Requires-Dist: asyncpg ; extra == 'asyncpg'
Provides-Extra: asyncpgsa
Requires-Dist: asyncpgsa ; extra == 'asyncpgsa'
Provides-Extra: develop
Requires-Dist: async-timeout ; extra == 'develop'
Requires-Dist: psycopg[pool] (<4,>=3.0) ; extra == 'develop'
Requires-Dist: aiopg[sa] (~=1.3.2) ; extra == 'develop'
Requires-Dist: asyncpg (~=0.24.0) ; extra == 'develop'
Requires-Dist: pytest (~=6.2.5) ; extra == 'develop'
Requires-Dist: pytest-cov (~=3.0.0) ; extra == 'develop'
Requires-Dist: pylama (~=7.7.1) ; extra == 'develop'
Requires-Dist: aiomisc (~=15.2.4) ; extra == 'develop'
Requires-Dist: mock (~=4.0.3) ; extra == 'develop'
Requires-Dist: sqlalchemy[asyncio] (~=1.4.27) ; extra == 'develop'
Requires-Dist: black (~=21.9b0) ; extra == 'develop'
Requires-Dist: tox (~=3.24) ; extra == 'develop'
Requires-Dist: twine ; extra == 'develop'
Requires-Dist: wheel ; extra == 'develop'
Provides-Extra: psycopg
Requires-Dist: psycopg[pool] (<4,>=3) ; extra == 'psycopg'
Provides-Extra: test
Requires-Dist: async-timeout ; extra == 'test'
Requires-Dist: psycopg[pool] (<4,>=3.0) ; extra == 'test'
Requires-Dist: aiopg[sa] (~=1.3.2) ; extra == 'test'
Requires-Dist: asyncpg (~=0.24.0) ; extra == 'test'
Requires-Dist: pytest (~=6.2.5) ; extra == 'test'
Requires-Dist: pytest-cov (~=3.0.0) ; extra == 'test'
Requires-Dist: aiomisc (~=15.2.4) ; extra == 'test'
Requires-Dist: mock (~=4.0.1) ; extra == 'test'
Requires-Dist: sqlalchemy[asyncio] (~=1.4.27) ; extra == 'test'
